rustycalc-0.2.0.dist-info/METADATA
rustycalc-0.2.0.dist-info/WHEEL
rustycalc-0.2.0.dist-info/licenses/LICENSE
rustycalc/addition/__init__.py
rustycalc/addition/sum.py
rustycalc/py.typed
rustycalc/__init__.py
rustycalc/subtraction/__init__.py
rustycalc/subtraction/diff.py
rustycalc/_core.pyi
rustycalc/_core.abi3.so
rustycalc-0.2.0.dist-info/RECORD
