Metadata-Version: 2.4
Name: rustycalc
Version: 0.2.0
Classifier: Development Status :: 4 - Beta
Classifier: Programming Language :: Python
Requires-Dist: maturin>=1.8.2
License-File: LICENSE
Summary: Add your description here
Keywords: calculator,python,rust,maturin,pyo3
Home-Page: https://github.com/deependujha/rustycalc
Author: Deependu Jha <deependujha21@gmail.com>
Author-email: Deependu Jha <deependujha21@gmail.com>
License: MIT
Requires-Python: >=3.8
Project-URL: Source Code, https://github.com/deependujha/rustycalc
